asitiger/__init__.py
asitiger/axis.py
asitiger/command.py
asitiger/errors.py
asitiger/secure.py
asitiger/serialconnection.py
asitiger/status.py
asitiger/tigercontroller.py
asitiger-0.0.5.dist-info/LICENSE
asitiger-0.0.5.dist-info/METADATA
asitiger-0.0.5.dist-info/WHEEL
asitiger-0.0.5.dist-info/top_level.txt
asitiger-0.0.5.dist-info/RECORD
