Metadata-Version: 2.1
Name: asitiger
Version: 0.0.5
Summary: A thin Python interface for communicating with ASI Tiger Controllers
Home-page: https://github.com/System1Bio/asitiger
Author: Chili Johnson
Author-email: chilij@chilij.com
License: UNKNOWN
Platform: UNKNOWN
Classifier: Programming Language :: Python :: 3
Classifier: License :: OSI Approved :: MIT License
Classifier: Operating System :: OS Independent
Requires-Python: >=3.6
Requires-Dist: pyserial (>=3.0)
Provides-Extra: dev
Requires-Dist: black (==19.10b0) ; extra == 'dev'
Requires-Dist: flake8-bugbear (==19.8.0) ; extra == 'dev'
Requires-Dist: pre-commit (>=2.7.1) ; extra == 'dev'
